verysimplemodule_xujz18/__init__.py
verysimplemodule_xujz18/add.py
verysimplemodule_xujz18/subtract.py
verysimplemodule_xujz18-0.0.1.dist-info/METADATA
verysimplemodule_xujz18-0.0.1.dist-info/WHEEL
verysimplemodule_xujz18-0.0.1.dist-info/top_level.txt
verysimplemodule_xujz18-0.0.1.dist-info/RECORD
